odoo/addons/ssi_l10n_id_taxform_pph_21_payslip/README.rst
odoo/addons/ssi_l10n_id_taxform_pph_21_payslip/__init__.py
odoo/addons/ssi_l10n_id_taxform_pph_21_payslip/__manifest__.py
odoo/addons/ssi_l10n_id_taxform_pph_21_payslip/i18n/ssi_l10n_id_taxform_pph_21_payslip.pot
odoo/addons/ssi_l10n_id_taxform_pph_21_payslip/models/__init__.py
odoo/addons/ssi_l10n_id_taxform_pph_21_payslip/models/hr_employee.py
odoo/addons/ssi_l10n_id_taxform_pph_21_payslip/models/hr_payslip.py
odoo/addons/ssi_l10n_id_taxform_pph_21_payslip/static/description/icon.png
odoo/addons/ssi_l10n_id_taxform_pph_21_payslip/views/hr_employee_views.xml
odoo/addons/ssi_l10n_id_taxform_pph_21_payslip/views/hr_payslip_views.xml
odoo14_addon_ssi_l10n_id_taxform_pph_21_payslip-14.0.1.1.0.dist-info/METADATA
odoo14_addon_ssi_l10n_id_taxform_pph_21_payslip-14.0.1.1.0.dist-info/WHEEL
odoo14_addon_ssi_l10n_id_taxform_pph_21_payslip-14.0.1.1.0.dist-info/top_level.txt
odoo14_addon_ssi_l10n_id_taxform_pph_21_payslip-14.0.1.1.0.dist-info/RECORD
