Metadata-Version: 2.1
Name: odoo14-addon-ssi_l10n_id_taxform_pph_21_payslip
Version: 14.0.1.1.0
Summary: Indonesia's Taxform - PPh 21 Computation On Payslip
Home-page: https://simetri-sinergi.id
Author: OpenSynergy Indonesia, PT. Simetri Sinergi Indonesia
License: AGPL-3
Classifier: Programming Language :: Python
Classifier: Framework :: Odoo
Classifier: Framework :: Odoo :: 14.0
Classifier: License :: OSI Approved :: GNU Affero General Public License v3
Requires-Python: >=3.6
Requires-Dist: odoo14-addon-ssi-hr-payroll
Requires-Dist: odoo14-addon-ssi-l10n-id-taxform-pph-21
Requires-Dist: odoo<14.1dev,>=14.0a
